pyxiaoheihe/__init__.py
pyxiaoheihe/account.py
pyxiaoheihe/community.py
pyxiaoheihe/error.py
pyxiaoheihe/game.py
pyxiaoheihe/index.py
pyxiaoheihe/network.py
pyxiaoheihe/static.py
pyxiaoheihe/utils.py
pyxiaoheihe-1.0.9.dist-info/LICENSE
pyxiaoheihe-1.0.9.dist-info/METADATA
pyxiaoheihe-1.0.9.dist-info/WHEEL
pyxiaoheihe-1.0.9.dist-info/top_level.txt
pyxiaoheihe-1.0.9.dist-info/RECORD
