Metadata-Version: 2.1
Name: pyxiaoheihe
Version: 1.0.9
Summary: 用Python实现的小黑盒客户端
Home-page: https://github.com/chr233/pyxiaoheihe
Author: Chr_
Author-email: chr@chrxw.com
License: UNKNOWN
Platform: UNKNOWN
Classifier: Programming Language :: Python :: 3
Classifier: License :: OSI Approved :: GNU Affero General Public License v3 or later (AGPLv3+)
Classifier: Operating System :: OS Independent
Requires-Dist: requests
Requires-Dist: pyDes
Requires-Dist: rsa
